{
  "generated_at": "2026-06-25 20:55:33",
  "metrics": {
    "total": 30,
    "success_count": 3,
    "fail_count": 27,
    "success_rate": 10.0,
    "fail_rate": 90.0,
    "wall_time": 381.072370900074,
    "qps": 0.07872520363819999,
    "success_qps": 0.007872520363819998,
    "tps": 0.007872520363819998,
    "avg_latency": 123398.40373666957,
    "success_avg_latency": 105030.35276678081,
    "min_latency": 103595.92330013402,
    "max_latency": 125579.48979991488,
    "p50_latency": 125417.89600008633,
    "p90_latency": 125529.15945986751,
    "p95_latency": 125549.4535850361,
    "p99_latency": 125575.28242195025,
    "avg_first_frame_latency": 123398.40373666957,
    "success_avg_first_frame_latency": 105030.35276678081,
    "min_first_frame_latency": 103595.92330013402,
    "max_first_frame_latency": 125579.48979991488,
    "p50_first_frame_latency": 125417.89600008633,
    "p90_first_frame_latency": 125529.15945986751,
    "p95_first_frame_latency": 125549.4535850361,
    "p99_first_frame_latency": 125575.28242195025,
    "avg_response_bytes": 741.3,
    "status_counter": {
      "200": 3,
      "502": 27
    },
    "error_counter": {
      "HTTPError: HTTP Error 502: Bad Gateway": 27
    },
    "rps_counter": {
      "108": 1,
      "125": 1,
      "126": 2,
      "127": 1,
      "128": 2,
      "129": 2,
      "130": 1,
      "233": 2,
      "250": 1,
      "251": 1,
      "252": 2,
      "254": 2,
      "255": 2,
      "359": 3,
      "376": 2,
      "377": 1,
      "378": 1,
      "379": 1,
      "380": 1,
      "381": 1
    },
    "body_template_metrics": [
      {
        "body_template_index": 1,
        "body_template_label": "Body #1",
        "total": 1,
        "success_count": 0,
        "fail_count": 1,
        "success_rate": 0.0,
        "avg_latency": 125399.38599988818,
        "p95_latency": 125399.38599988818,
        "avg_first_frame_latency": 125399.38599988818,
        "p95_first_frame_latency": 125399.38599988818,
        "status_counter": {
          "502": 1
        },
        "error_counter": {
          "HTTPError: HTTP Error 502: Bad Gateway": 1
        }
      },
      {
        "body_template_index": 2,
        "body_template_label": "Body #2",
        "total": 2,
        "success_count": 0,
        "fail_count": 2,
        "success_rate": 0.0,
        "avg_latency": 125512.87974999286,
        "p95_latency": 125528.71538503096,
        "avg_first_frame_latency": 125512.87974999286,
        "p95_first_frame_latency": 125528.71538503096,
        "status_counter": {
          "502": 2
        },
        "error_counter": {
          "HTTPError: HTTP Error 502: Bad Gateway": 2
        }
      },
      {
        "body_template_index": 3,
        "body_template_label": "Body #3",
        "total": 2,
        "success_count": 2,
        "fail_count": 0,
        "success_rate": 100.0,
        "avg_latency": 104570.57580014225,
        "p95_latency": 105447.76305014966,
        "avg_first_frame_latency": 104570.57580014225,
        "p95_first_frame_latency": 105447.76305014966,
        "status_counter": {
          "200": 2
        },
        "error_counter": {}
      },
      {
        "body_template_index": 4,
        "body_template_label": "Body #4",
        "total": 1,
        "success_count": 0,
        "fail_count": 1,
        "success_rate": 0.0,
        "avg_latency": 125306.71239993535,
        "p95_latency": 125306.71239993535,
        "avg_first_frame_latency": 125306.71239993535,
        "p95_first_frame_latency": 125306.71239993535,
        "status_counter": {
          "502": 1
        },
        "error_counter": {
          "HTTPError: HTTP Error 502: Bad Gateway": 1
        }
      },
      {
        "body_template_index": 5,
        "body_template_label": "Body #5",
        "total": 3,
        "success_count": 1,
        "fail_count": 2,
        "success_rate": 33.33333333333333,
        "avg_latency": 118983.27446666856,
        "p95_latency": 125502.32726999093,
        "avg_first_frame_latency": 118983.27446666856,
        "p95_first_frame_latency": 125502.32726999093,
        "status_counter": {
          "200": 1,
          "502": 2
        },
        "error_counter": {
          "HTTPError: HTTP Error 502: Bad Gateway": 2
        }
      },
      {
        "body_template_index": 6,
        "body_template_label": "Body #6",
        "total": 1,
        "success_count": 0,
        "fail_count": 1,
        "success_rate": 0.0,
        "avg_latency": 125377.3633998353,
        "p95_latency": 125377.3633998353,
        "avg_first_frame_latency": 125377.3633998353,
        "p95_first_frame_latency": 125377.3633998353,
        "status_counter": {
          "502": 1
        },
        "error_counter": {
          "HTTPError: HTTP Error 502: Bad Gateway": 1
        }
      },
      {
        "body_template_index": 7,
        "body_template_label": "Body #7",
        "total": 2,
        "success_count": 0,
        "fail_count": 2,
        "success_rate": 0.0,
        "avg_latency": 125439.25705004949,
        "p95_latency": 125464.36835509958,
        "avg_first_frame_latency": 125439.25705004949,
        "p95_first_frame_latency": 125464.36835509958,
        "status_counter": {
          "502": 2
        },
        "error_counter": {
          "HTTPError: HTTP Error 502: Bad Gateway": 2
        }
      },
      {
        "body_template_index": 8,
        "body_template_label": "Body #8",
        "total": 6,
        "success_count": 0,
        "fail_count": 6,
        "success_rate": 0.0,
        "avg_latency": 125532.0481666907,
        "p95_latency": 125575.86274994537,
        "avg_first_frame_latency": 125532.0481666907,
        "p95_first_frame_latency": 125575.86274994537,
        "status_counter": {
          "502": 6
        },
        "error_counter": {
          "HTTPError: HTTP Error 502: Bad Gateway": 6
        }
      },
      {
        "body_template_index": 9,
        "body_template_label": "Body #9",
        "total": 7,
        "success_count": 0,
        "fail_count": 7,
        "success_rate": 0.0,
        "avg_latency": 125388.07061424346,
        "p95_latency": 125449.66292998288,
        "avg_first_frame_latency": 125388.07061424346,
        "p95_first_frame_latency": 125449.66292998288,
        "status_counter": {
          "502": 7
        },
        "error_counter": {
          "HTTPError: HTTP Error 502: Bad Gateway": 7
        }
      },
      {
        "body_template_index": 10,
        "body_template_label": "Body #10",
        "total": 2,
        "success_count": 0,
        "fail_count": 2,
        "success_rate": 0.0,
        "avg_latency": 125367.34185006935,
        "p95_latency": 125381.23735500267,
        "avg_first_frame_latency": 125367.34185006935,
        "p95_first_frame_latency": 125381.23735500267,
        "status_counter": {
          "502": 2
        },
        "error_counter": {
          "HTTPError: HTTP Error 502: Bad Gateway": 2
        }
      },
      {
        "body_template_index": 11,
        "body_template_label": "Body #11",
        "total": 3,
        "success_count": 0,
        "fail_count": 3,
        "success_rate": 0.0,
        "avg_latency": 125409.9782333554,
        "p95_latency": 125448.24040986132,
        "avg_first_frame_latency": 125409.9782333554,
        "p95_first_frame_latency": 125448.24040986132,
        "status_counter": {
          "502": 3
        },
        "error_counter": {
          "HTTPError: HTTP Error 502: Bad Gateway": 3
        }
      }
    ]
  },
  "results": [
    {
      "request_id": 5,
      "success": true,
      "status_code": 200,
      "error": "",
      "latency_ms": 105949.90670005791,
      "first_frame_latency_ms": 105949.90670005791,
      "response_bytes": 10785,
      "start_time": "2026-06-25 20:49:14.915",
      "end_time": "2026-06-25 20:51:00.864",
      "relative_end_second": 108,
      "body_template_index": 5,
      "body_template_label": "Body #5",
      "debug_info": ""
    },
    {
      "request_id": 1,
      "success": false,
      "status_code": 502,
      "error": "HTTPError: HTTP Error 502: Bad Gateway",
      "latency_ms": 125373.08289995417,
      "first_frame_latency_ms": 125373.08289995417,
      "response_bytes": 0,
      "start_time": "2026-06-25 20:49:12.688",
      "end_time": "2026-06-25 20:51:18.061",
      "relative_end_second": 125,
      "body_template_index": 9,
      "body_template_label": "Body #9",
      "debug_info": ""
    },
    {
      "request_id": 2,
      "success": false,
      "status_code": 502,
      "error": "HTTPError: HTTP Error 502: Bad Gateway",
      "latency_ms": 125579.48979991488,
      "first_frame_latency_ms": 125579.48979991488,
      "response_bytes": 0,
      "start_time": "2026-06-25 20:49:13.245",
      "end_time": "2026-06-25 20:51:18.824",
      "relative_end_second": 126,
      "body_template_index": 8,
      "body_template_label": "Body #8",
      "debug_info": ""
    },
    {
      "request_id": 3,
      "success": false,
      "status_code": 502,
      "error": "HTTPError: HTTP Error 502: Bad Gateway",
      "latency_ms": 125515.61510004103,
      "first_frame_latency_ms": 125515.61510004103,
      "response_bytes": 0,
      "start_time": "2026-06-25 20:49:13.801",
      "end_time": "2026-06-25 20:51:19.317",
      "relative_end_second": 126,
      "body_template_index": 8,
      "body_template_label": "Body #8",
      "debug_info": ""
    },
    {
      "request_id": 4,
      "success": false,
      "status_code": 502,
      "error": "HTTPError: HTTP Error 502: Bad Gateway",
      "latency_ms": 125381.97169988416,
      "first_frame_latency_ms": 125381.97169988416,
      "response_bytes": 0,
      "start_time": "2026-06-25 20:49:14.358",
      "end_time": "2026-06-25 20:51:19.740",
      "relative_end_second": 127,
      "body_template_index": 9,
      "body_template_label": "Body #9",
      "debug_info": ""
    },
    {
      "request_id": 6,
      "success": false,
      "status_code": 502,
      "error": "HTTPError: HTTP Error 502: Bad Gateway",
      "latency_ms": 125354.09729997627,
      "first_frame_latency_ms": 125354.09729997627,
      "response_bytes": 0,
      "start_time": "2026-06-25 20:49:15.472",
      "end_time": "2026-06-25 20:51:20.825",
      "relative_end_second": 128,
      "body_template_index": 9,
      "body_template_label": "Body #9",
      "debug_info": ""
    },
    {
      "request_id": 7,
      "success": false,
      "status_code": 502,
      "error": "HTTPError: HTTP Error 502: Bad Gateway",
      "latency_ms": 125497.84660013393,
      "first_frame_latency_ms": 125497.84660013393,
      "response_bytes": 0,
      "start_time": "2026-06-25 20:49:16.029",
      "end_time": "2026-06-25 20:51:21.526",
      "relative_end_second": 128,
      "body_template_index": 8,
      "body_template_label": "Body #8",
      "debug_info": ""
    },
    {
      "request_id": 8,
      "success": false,
      "status_code": 502,
      "error": "HTTPError: HTTP Error 502: Bad Gateway",
      "latency_ms": 125411.35559999384,
      "first_frame_latency_ms": 125411.35559999384,
      "response_bytes": 0,
      "start_time": "2026-06-25 20:49:16.585",
      "end_time": "2026-06-25 20:51:21.995",
      "relative_end_second": 129,
      "body_template_index": 7,
      "body_template_label": "Body #7",
      "debug_info": ""
    },
    {
      "request_id": 9,
      "success": false,
      "status_code": 502,
      "error": "HTTPError: HTTP Error 502: Bad Gateway",
      "latency_ms": 125502.91949999519,
      "first_frame_latency_ms": 125502.91949999519,
      "response_bytes": 0,
      "start_time": "2026-06-25 20:49:17.141",
      "end_time": "2026-06-25 20:51:22.643",
      "relative_end_second": 129,
      "body_template_index": 5,
      "body_template_label": "Body #5",
      "debug_info": ""
    },
    {
      "request_id": 10,
      "success": false,
      "status_code": 502,
      "error": "HTTPError: HTTP Error 502: Bad Gateway",
      "latency_ms": 125399.38599988818,
      "first_frame_latency_ms": 125399.38599988818,
      "response_bytes": 0,
      "start_time": "2026-06-25 20:49:17.698",
      "end_time": "2026-06-25 20:51:23.097",
      "relative_end_second": 130,
      "body_template_index": 1,
      "body_template_label": "Body #1",
      "debug_info": ""
    },
    {
      "request_id": 11,
      "success": false,
      "status_code": 502,
      "error": "HTTPError: HTTP Error 502: Bad Gateway",
      "latency_ms": 125495.28459995054,
      "first_frame_latency_ms": 125495.28459995054,
      "response_bytes": 0,
      "start_time": "2026-06-25 20:51:00.865",
      "end_time": "2026-06-25 20:53:06.359",
      "relative_end_second": 233,
      "body_template_index": 2,
      "body_template_label": "Body #2",
      "debug_info": ""
    },
    {
      "request_id": 16,
      "success": true,
      "status_code": 200,
      "error": "",
      "latency_ms": 105545.22830015048,
      "first_frame_latency_ms": 105545.22830015048,
      "response_bytes": 5699,
      "start_time": "2026-06-25 20:51:20.826",
      "end_time": "2026-06-25 20:53:06.370",
      "relative_end_second": 233,
      "body_template_index": 3,
      "body_template_label": "Body #3",
      "debug_info": ""
    },
    {
      "request_id": 12,
      "success": false,
      "status_code": 502,
      "error": "HTTPError: HTTP Error 502: Bad Gateway",
      "latency_ms": 125351.90240014344,
      "first_frame_latency_ms": 125351.90240014344,
      "response_bytes": 0,
      "start_time": "2026-06-25 20:51:18.061",
      "end_time": "2026-06-25 20:53:23.412",
      "relative_end_second": 250,
      "body_template_index": 10,
      "body_template_label": "Body #10",
      "debug_info": ""
    },
    {
      "request_id": 13,
      "success": false,
      "status_code": 502,
      "error": "HTTPError: HTTP Error 502: Bad Gateway",
      "latency_ms": 125496.9971999526,
      "first_frame_latency_ms": 125496.9971999526,
      "response_bytes": 0,
      "start_time": "2026-06-25 20:51:18.824",
      "end_time": "2026-06-25 20:53:24.320",
      "relative_end_second": 251,
      "body_template_index": 5,
      "body_template_label": "Body #5",
      "debug_info": ""
    },
    {
      "request_id": 14,
      "success": false,
      "status_code": 502,
      "error": "HTTPError: HTTP Error 502: Bad Gateway",
      "latency_ms": 125530.47490003519,
      "first_frame_latency_ms": 125530.47490003519,
      "response_bytes": 0,
      "start_time": "2026-06-25 20:51:19.317",
      "end_time": "2026-06-25 20:53:24.846",
      "relative_end_second": 252,
      "body_template_index": 2,
      "body_template_label": "Body #2",
      "debug_info": ""
    },
    {
      "request_id": 15,
      "success": false,
      "status_code": 502,
      "error": "HTTPError: HTTP Error 502: Bad Gateway",
      "latency_ms": 125505.34260016866,
      "first_frame_latency_ms": 125505.34260016866,
      "response_bytes": 0,
      "start_time": "2026-06-25 20:51:19.740",
      "end_time": "2026-06-25 20:53:25.244",
      "relative_end_second": 252,
      "body_template_index": 8,
      "body_template_label": "Body #8",
      "debug_info": ""
    },
    {
      "request_id": 17,
      "success": false,
      "status_code": 502,
      "error": "HTTPError: HTTP Error 502: Bad Gateway",
      "latency_ms": 125424.43640017882,
      "first_frame_latency_ms": 125424.43640017882,
      "response_bytes": 0,
      "start_time": "2026-06-25 20:51:21.526",
      "end_time": "2026-06-25 20:53:26.949",
      "relative_end_second": 254,
      "body_template_index": 11,
      "body_template_label": "Body #11",
      "debug_info": ""
    },
    {
      "request_id": 18,
      "success": false,
      "status_code": 502,
      "error": "HTTPError: HTTP Error 502: Bad Gateway",
      "latency_ms": 125446.75519992597,
      "first_frame_latency_ms": 125446.75519992597,
      "response_bytes": 0,
      "start_time": "2026-06-25 20:51:21.996",
      "end_time": "2026-06-25 20:53:27.442",
      "relative_end_second": 254,
      "body_template_index": 9,
      "body_template_label": "Body #9",
      "debug_info": ""
    },
    {
      "request_id": 19,
      "success": false,
      "status_code": 502,
      "error": "HTTPError: HTTP Error 502: Bad Gateway",
      "latency_ms": 125529.01329984888,
      "first_frame_latency_ms": 125529.01329984888,
      "response_bytes": 0,
      "start_time": "2026-06-25 20:51:22.644",
      "end_time": "2026-06-25 20:53:28.172",
      "relative_end_second": 255,
      "body_template_index": 8,
      "body_template_label": "Body #8",
      "debug_info": ""
    },
    {
      "request_id": 20,
      "success": false,
      "status_code": 502,
      "error": "HTTPError: HTTP Error 502: Bad Gateway",
      "latency_ms": 125354.61300006136,
      "first_frame_latency_ms": 125354.61300006136,
      "response_bytes": 0,
      "start_time": "2026-06-25 20:51:23.098",
      "end_time": "2026-06-25 20:53:28.451",
      "relative_end_second": 255,
      "body_template_index": 11,
      "body_template_label": "Body #11",
      "debug_info": ""
    },
    {
      "request_id": 29,
      "success": true,
      "status_code": 200,
      "error": "",
      "latency_ms": 103595.92330013402,
      "first_frame_latency_ms": 103595.92330013402,
      "response_bytes": 5755,
      "start_time": "2026-06-25 20:53:28.172",
      "end_time": "2026-06-25 20:55:11.767",
      "relative_end_second": 359,
      "body_template_index": 3,
      "body_template_label": "Body #3",
      "debug_info": ""
    },
    {
      "request_id": 21,
      "success": false,
      "status_code": 502,
      "error": "HTTPError: HTTP Error 502: Bad Gateway",
      "latency_ms": 125450.88529982604,
      "first_frame_latency_ms": 125450.88529982604,
      "response_bytes": 0,
      "start_time": "2026-06-25 20:53:06.359",
      "end_time": "2026-06-25 20:55:11.810",
      "relative_end_second": 359,
      "body_template_index": 11,
      "body_template_label": "Body #11",
      "debug_info": ""
    },
    {
      "request_id": 22,
      "success": false,
      "status_code": 502,
      "error": "HTTPError: HTTP Error 502: Bad Gateway",
      "latency_ms": 125450.90910000727,
      "first_frame_latency_ms": 125450.90910000727,
      "response_bytes": 0,
      "start_time": "2026-06-25 20:53:06.370",
      "end_time": "2026-06-25 20:55:11.821",
      "relative_end_second": 359,
      "body_template_index": 9,
      "body_template_label": "Body #9",
      "debug_info": ""
    },
    {
      "request_id": 23,
      "success": false,
      "status_code": 502,
      "error": "HTTPError: HTTP Error 502: Bad Gateway",
      "latency_ms": 125382.78129999526,
      "first_frame_latency_ms": 125382.78129999526,
      "response_bytes": 0,
      "start_time": "2026-06-25 20:53:23.412",
      "end_time": "2026-06-25 20:55:28.795",
      "relative_end_second": 376,
      "body_template_index": 10,
      "body_template_label": "Body #10",
      "debug_info": ""
    },
    {
      "request_id": 24,
      "success": false,
      "status_code": 502,
      "error": "HTTPError: HTTP Error 502: Bad Gateway",
      "latency_ms": 125365.12429988943,
      "first_frame_latency_ms": 125365.12429988943,
      "response_bytes": 0,
      "start_time": "2026-06-25 20:53:24.320",
      "end_time": "2026-06-25 20:55:29.685",
      "relative_end_second": 376,
      "body_template_index": 9,
      "body_template_label": "Body #9",
      "debug_info": ""
    },
    {
      "request_id": 25,
      "success": false,
      "status_code": 502,
      "error": "HTTPError: HTTP Error 502: Bad Gateway",
      "latency_ms": 125344.55380006693,
      "first_frame_latency_ms": 125344.55380006693,
      "response_bytes": 0,
      "start_time": "2026-06-25 20:53:24.847",
      "end_time": "2026-06-25 20:55:30.190",
      "relative_end_second": 377,
      "body_template_index": 9,
      "body_template_label": "Body #9",
      "debug_info": ""
    },
    {
      "request_id": 26,
      "success": false,
      "status_code": 502,
      "error": "HTTPError: HTTP Error 502: Bad Gateway",
      "latency_ms": 125564.98160003684,
      "first_frame_latency_ms": 125564.98160003684,
      "response_bytes": 0,
      "start_time": "2026-06-25 20:53:25.244",
      "end_time": "2026-06-25 20:55:30.809",
      "relative_end_second": 378,
      "body_template_index": 8,
      "body_template_label": "Body #8",
      "debug_info": ""
    },
    {
      "request_id": 27,
      "success": false,
      "status_code": 502,
      "error": "HTTPError: HTTP Error 502: Bad Gateway",
      "latency_ms": 125377.3633998353,
      "first_frame_latency_ms": 125377.3633998353,
      "response_bytes": 0,
      "start_time": "2026-06-25 20:53:26.950",
      "end_time": "2026-06-25 20:55:32.326",
      "relative_end_second": 379,
      "body_template_index": 6,
      "body_template_label": "Body #6",
      "debug_info": ""
    },
    {
      "request_id": 28,
      "success": false,
      "status_code": 502,
      "error": "HTTPError: HTTP Error 502: Bad Gateway",
      "latency_ms": 125467.15850010514,
      "first_frame_latency_ms": 125467.15850010514,
      "response_bytes": 0,
      "start_time": "2026-06-25 20:53:27.442",
      "end_time": "2026-06-25 20:55:32.909",
      "relative_end_second": 380,
      "body_template_index": 7,
      "body_template_label": "Body #7",
      "debug_info": ""
    },
    {
      "request_id": 30,
      "success": false,
      "status_code": 502,
      "error": "HTTPError: HTTP Error 502: Bad Gateway",
      "latency_ms": 125306.71239993535,
      "first_frame_latency_ms": 125306.71239993535,
      "response_bytes": 0,
      "start_time": "2026-06-25 20:53:28.451",
      "end_time": "2026-06-25 20:55:33.757",
      "relative_end_second": 381,
      "body_template_index": 4,
      "body_template_label": "Body #4",
      "debug_info": ""
    }
  ]
}