{
  "generated_at": "2026-06-25 19:39:16",
  "metrics": {
    "total": 100,
    "success_count": 100,
    "fail_count": 0,
    "success_rate": 100.0,
    "fail_rate": 0.0,
    "wall_time": 288.143209700007,
    "qps": 0.3470496497353259,
    "success_qps": 0.3470496497353259,
    "tps": 0.3470496497353259,
    "avg_latency": 22330.1843089913,
    "success_avg_latency": 22330.1843089913,
    "min_latency": 10493.282199837267,
    "max_latency": 93265.70870005526,
    "p50_latency": 17164.44445005618,
    "p90_latency": 44236.81486987043,
    "p95_latency": 51818.4037199826,
    "p99_latency": 64278.18536587075,
    "avg_first_frame_latency": 5681.38053199742,
    "success_avg_first_frame_latency": 5681.38053199742,
    "min_first_frame_latency": 842.1638999134302,
    "max_first_frame_latency": 10882.775200065225,
    "p50_first_frame_latency": 5625.790300080553,
    "p90_first_frame_latency": 9152.921219938435,
    "p95_first_frame_latency": 9881.572525016962,
    "p99_first_frame_latency": 10609.810024013279,
    "avg_response_bytes": 128910.11,
    "status_counter": {
      "0": 100
    },
    "error_counter": {},
    "rps_counter": {
      "12": 1,
      "13": 1,
      "15": 1,
      "19": 2,
      "24": 1,
      "27": 1,
      "28": 1,
      "31": 1,
      "32": 1,
      "37": 1,
      "41": 1,
      "44": 1,
      "49": 1,
      "52": 1,
      "55": 1,
      "56": 1,
      "59": 1,
      "62": 1,
      "63": 2,
      "65": 1,
      "69": 1,
      "73": 1,
      "74": 1,
      "76": 1,
      "77": 1,
      "81": 1,
      "85": 1,
      "88": 1,
      "91": 1,
      "92": 1,
      "94": 1,
      "98": 1,
      "99": 2,
      "102": 1,
      "104": 2,
      "106": 1,
      "109": 1,
      "112": 1,
      "115": 1,
      "116": 1,
      "117": 1,
      "121": 1,
      "122": 1,
      "123": 1,
      "124": 1,
      "125": 1,
      "128": 1,
      "132": 1,
      "136": 1,
      "137": 1,
      "139": 1,
      "140": 1,
      "143": 2,
      "145": 1,
      "148": 1,
      "151": 1,
      "155": 1,
      "159": 1,
      "160": 2,
      "162": 1,
      "164": 1,
      "167": 1,
      "170": 1,
      "172": 2,
      "181": 2,
      "182": 2,
      "186": 1,
      "187": 2,
      "188": 1,
      "193": 1,
      "194": 1,
      "197": 1,
      "198": 1,
      "199": 2,
      "203": 2,
      "205": 1,
      "206": 1,
      "209": 1,
      "211": 1,
      "213": 1,
      "219": 1,
      "220": 1,
      "221": 1,
      "222": 1,
      "223": 1,
      "224": 1,
      "237": 1,
      "288": 1
    },
    "body_template_metrics": [
      {
        "body_template_index": 1,
        "body_template_label": "Body #1",
        "total": 10,
        "success_count": 10,
        "fail_count": 0,
        "success_rate": 100.0,
        "avg_latency": 36069.57066000905,
        "p95_latency": 76499.79261497504,
        "avg_first_frame_latency": 7611.198700009845,
        "p95_first_frame_latency": 10727.069035009481,
        "status_counter": {
          "0": 10
        },
        "error_counter": {}
      },
      {
        "body_template_index": 2,
        "body_template_label": "Body #2",
        "total": 10,
        "success_count": 10,
        "fail_count": 0,
        "success_rate": 100.0,
        "avg_latency": 16619.235730031505,
        "p95_latency": 23923.159484949436,
        "avg_first_frame_latency": 5619.343710015528,
        "p95_first_frame_latency": 8682.56824502023,
        "status_counter": {
          "0": 10
        },
        "error_counter": {}
      },
      {
        "body_template_index": 3,
        "body_template_label": "Body #3",
        "total": 10,
        "success_count": 10,
        "fail_count": 0,
        "success_rate": 100.0,
        "avg_latency": 15393.839300028048,
        "p95_latency": 21836.534700042102,
        "avg_first_frame_latency": 4158.251170022413,
        "p95_first_frame_latency": 7668.7195201288,
        "status_counter": {
          "0": 10
        },
        "error_counter": {}
      },
      {
        "body_template_index": 4,
        "body_template_label": "Body #4",
        "total": 10,
        "success_count": 10,
        "fail_count": 0,
        "success_rate": 100.0,
        "avg_latency": 44880.842669913545,
        "p95_latency": 58796.42246991862,
        "avg_first_frame_latency": 5235.240019974299,
        "p95_first_frame_latency": 7273.923784960062,
        "status_counter": {
          "0": 10
        },
        "error_counter": {}
      },
      {
        "body_template_index": 5,
        "body_template_label": "Body #5",
        "total": 10,
        "success_count": 10,
        "fail_count": 0,
        "success_rate": 100.0,
        "avg_latency": 15600.114040006883,
        "p95_latency": 20126.259199879136,
        "avg_first_frame_latency": 5697.836250043474,
        "p95_first_frame_latency": 8540.170339914039,
        "status_counter": {
          "0": 10
        },
        "error_counter": {}
      },
      {
        "body_template_index": 6,
        "body_template_label": "Body #6",
        "total": 10,
        "success_count": 10,
        "fail_count": 0,
        "success_rate": 100.0,
        "avg_latency": 20568.233060021885,
        "p95_latency": 24277.785905078053,
        "avg_first_frame_latency": 5020.380510017276,
        "p95_first_frame_latency": 8596.736350050198,
        "status_counter": {
          "0": 10
        },
        "error_counter": {}
      },
      {
        "body_template_index": 7,
        "body_template_label": "Body #7",
        "total": 10,
        "success_count": 10,
        "fail_count": 0,
        "success_rate": 100.0,
        "avg_latency": 24649.39614997711,
        "p95_latency": 52018.388729973245,
        "avg_first_frame_latency": 5144.667369965464,
        "p95_first_frame_latency": 8668.512394977735,
        "status_counter": {
          "0": 10
        },
        "error_counter": {}
      },
      {
        "body_template_index": 8,
        "body_template_label": "Body #8",
        "total": 10,
        "success_count": 10,
        "fail_count": 0,
        "success_rate": 100.0,
        "avg_latency": 15915.33559996169,
        "p95_latency": 21497.37812003587,
        "avg_first_frame_latency": 5287.052729958668,
        "p95_first_frame_latency": 7506.861114921048,
        "status_counter": {
          "0": 10
        },
        "error_counter": {}
      },
      {
        "body_template_index": 9,
        "body_template_label": "Body #9",
        "total": 10,
        "success_count": 10,
        "fail_count": 0,
        "success_rate": 100.0,
        "avg_latency": 17135.496299923398,
        "p95_latency": 24747.65037992038,
        "avg_first_frame_latency": 5939.055599970743,
        "p95_first_frame_latency": 8513.066264952067,
        "status_counter": {
          "0": 10
        },
        "error_counter": {}
      },
      {
        "body_template_index": 10,
        "body_template_label": "Body #10",
        "total": 10,
        "success_count": 10,
        "fail_count": 0,
        "success_rate": 100.0,
        "avg_latency": 16469.779580039904,
        "p95_latency": 22500.592955038886,
        "avg_first_frame_latency": 7100.779259996489,
        "p95_first_frame_latency": 10496.375300060026,
        "status_counter": {
          "0": 10
        },
        "error_counter": {}
      }
    ]
  },
  "results": [
    {
      "request_id": 2,
      "success": true,
      "status_code": 0,
      "error": "",
      "latency_ms": 10904.379299841821,
      "first_frame_latency_ms": 859.6878999378532,
      "response_bytes": 67965,
      "start_time": "2026-06-25 19:34:29.324",
      "end_time": "2026-06-25 19:34:40.229",
      "relative_end_second": 12,
      "body_template_index": 2,
      "body_template_label": "Body #2",
      "debug_info": "target=47.94.77.104:8097, method_path=/com.tcl.xr.service.AskAiService/chat, request=com.tcl.xr.message.AskAiRequest, response=com.tcl.xr.message.AskAiResponse, server_streaming=True, payload_bytes=357"
    },
    {
      "request_id": 3,
      "success": true,
      "status_code": 0,
      "error": "",
      "latency_ms": 11703.573500039056,
      "first_frame_latency_ms": 842.1638999134302,
      "response_bytes": 66103,
      "start_time": "2026-06-25 19:34:30.436",
      "end_time": "2026-06-25 19:34:42.139",
      "relative_end_second": 13,
      "body_template_index": 3,
      "body_template_label": "Body #3",
      "debug_info": "target=47.94.77.104:8097, method_path=/com.tcl.xr.service.AskAiService/chat, request=com.tcl.xr.message.AskAiRequest, response=com.tcl.xr.message.AskAiResponse, server_streaming=True, payload_bytes=327"
    },
    {
      "request_id": 5,
      "success": true,
      "status_code": 0,
      "error": "",
      "latency_ms": 11092.145300004631,
      "first_frame_latency_ms": 1028.8023999892175,
      "response_bytes": 76373,
      "start_time": "2026-06-25 19:34:32.660",
      "end_time": "2026-06-25 19:34:43.753",
      "relative_end_second": 15,
      "body_template_index": 5,
      "body_template_label": "Body #5",
      "debug_info": "target=47.94.77.104:8097, method_path=/com.tcl.xr.service.AskAiService/chat, request=com.tcl.xr.message.AskAiRequest, response=com.tcl.xr.message.AskAiResponse, server_streaming=True, payload_bytes=442"
    },
    {
      "request_id": 9,
      "success": true,
      "status_code": 0,
      "error": "",
      "latency_ms": 10493.282199837267,
      "first_frame_latency_ms": 3927.0071999635547,
      "response_bytes": 47156,
      "start_time": "2026-06-25 19:34:37.108",
      "end_time": "2026-06-25 19:34:47.600",
      "relative_end_second": 19,
      "body_template_index": 9,
      "body_template_label": "Body #9",
      "debug_info": "target=47.94.77.104:8097, method_path=/com.tcl.xr.service.AskAiService/chat, request=com.tcl.xr.message.AskAiRequest, response=com.tcl.xr.message.AskAiResponse, server_streaming=True, payload_bytes=318"
    },
    {
      "request_id": 8,
      "success": true,
      "status_code": 0,
      "error": "",
      "latency_ms": 11628.563799895346,
      "first_frame_latency_ms": 1386.9451999198645,
      "response_bytes": 73852,
      "start_time": "2026-06-25 19:34:35.996",
      "end_time": "2026-06-25 19:34:47.624",
      "relative_end_second": 19,
      "body_template_index": 8,
      "body_template_label": "Body #8",
      "debug_info": "target=47.94.77.104:8097, method_path=/com.tcl.xr.service.AskAiService/chat, request=com.tcl.xr.message.AskAiRequest, response=com.tcl.xr.message.AskAiResponse, server_streaming=True, payload_bytes=312"
    },
    {
      "request_id": 10,
      "success": true,
      "status_code": 0,
      "error": "",
      "latency_ms": 14671.913599828258,
      "first_frame_latency_ms": 4795.774800004438,
      "response_bytes": 66450,
      "start_time": "2026-06-25 19:34:38.220",
      "end_time": "2026-06-25 19:34:52.892",
      "relative_end_second": 24,
      "body_template_index": 10,
      "body_template_label": "Body #10",
      "debug_info": "target=47.94.77.104:8097, method_path=/com.tcl.xr.service.AskAiService/chat, request=com.tcl.xr.message.AskAiRequest, response=com.tcl.xr.message.AskAiResponse, server_streaming=True, payload_bytes=300"
    },
    {
      "request_id": 12,
      "success": true,
      "status_code": 0,
      "error": "",
      "latency_ms": 13337.74400013499,
      "first_frame_latency_ms": 6990.223499946296,
      "response_bytes": 54133,
      "start_time": "2026-06-25 19:34:42.140",
      "end_time": "2026-06-25 19:34:55.477",
      "relative_end_second": 27,
      "body_template_index": 2,
      "body_template_label": "Body #2",
      "debug_info": "target=47.94.77.104:8097, method_path=/com.tcl.xr.service.AskAiService/chat, request=com.tcl.xr.message.AskAiRequest, response=com.tcl.xr.message.AskAiResponse, server_streaming=True, payload_bytes=357"
    },
    {
      "request_id": 6,
      "success": true,
      "status_code": 0,
      "error": "",
      "latency_ms": 22765.663699945435,
      "first_frame_latency_ms": 1087.333899922669,
      "response_bytes": 188459,
      "start_time": "2026-06-25 19:34:33.772",
      "end_time": "2026-06-25 19:34:56.538",
      "relative_end_second": 28,
      "body_template_index": 6,
      "body_template_label": "Body #6",
      "debug_info": "target=47.94.77.104:8097, method_path=/com.tcl.xr.service.AskAiService/chat, request=com.tcl.xr.message.AskAiRequest, response=com.tcl.xr.message.AskAiResponse, server_streaming=True, payload_bytes=395"
    },
    {
      "request_id": 13,
      "success": true,
      "status_code": 0,
      "error": "",
      "latency_ms": 16254.523399984464,
      "first_frame_latency_ms": 5161.112600006163,
      "response_bytes": 77608,
      "start_time": "2026-06-25 19:34:43.753",
      "end_time": "2026-06-25 19:35:00.007",
      "relative_end_second": 31,
      "body_template_index": 3,
      "body_template_label": "Body #3",
      "debug_info": "target=47.94.77.104:8097, method_path=/com.tcl.xr.service.AskAiService/chat, request=com.tcl.xr.message.AskAiRequest, response=com.tcl.xr.message.AskAiResponse, server_streaming=True, payload_bytes=327"
    },
    {
      "request_id": 4,
      "success": true,
      "status_code": 0,
      "error": "",
      "latency_ms": 28920.0366998557,
      "first_frame_latency_ms": 1183.9674999937415,
      "response_bytes": 185465,
      "start_time": "2026-06-25 19:34:31.548",
      "end_time": "2026-06-25 19:35:00.467",
      "relative_end_second": 32,
      "body_template_index": 4,
      "body_template_label": "Body #4",
      "debug_info": "target=47.94.77.104:8097, method_path=/com.tcl.xr.service.AskAiService/chat, request=com.tcl.xr.message.AskAiRequest, response=com.tcl.xr.message.AskAiResponse, server_streaming=True, payload_bytes=372"
    },
    {
      "request_id": 15,
      "success": true,
      "status_code": 0,
      "error": "",
      "latency_ms": 17686.983899911866,
      "first_frame_latency_ms": 9080.275099957362,
      "response_bytes": 71852,
      "start_time": "2026-06-25 19:34:47.624",
      "end_time": "2026-06-25 19:35:05.311",
      "relative_end_second": 37,
      "body_template_index": 5,
      "body_template_label": "Body #5",
      "debug_info": "target=47.94.77.104:8097, method_path=/com.tcl.xr.service.AskAiService/chat, request=com.tcl.xr.message.AskAiRequest, response=com.tcl.xr.message.AskAiResponse, server_streaming=True, payload_bytes=442"
    },
    {
      "request_id": 17,
      "success": true,
      "status_code": 0,
      "error": "",
      "latency_ms": 14512.281199917197,
      "first_frame_latency_ms": 5520.3877000603825,
      "response_bytes": 79466,
      "start_time": "2026-06-25 19:34:55.478",
      "end_time": "2026-06-25 19:35:09.989",
      "relative_end_second": 41,
      "body_template_index": 7,
      "body_template_label": "Body #7",
      "debug_info": "target=47.94.77.104:8097, method_path=/com.tcl.xr.service.AskAiService/chat, request=com.tcl.xr.message.AskAiRequest, response=com.tcl.xr.message.AskAiResponse, server_streaming=True, payload_bytes=369"
    },
    {
      "request_id": 16,
      "success": true,
      "status_code": 0,
      "error": "",
      "latency_ms": 19941.328700166196,
      "first_frame_latency_ms": 4700.619700131938,
      "response_bytes": 141682,
      "start_time": "2026-06-25 19:34:52.892",
      "end_time": "2026-06-25 19:35:12.833",
      "relative_end_second": 44,
      "body_template_index": 6,
      "body_template_label": "Body #6",
      "debug_info": "target=47.94.77.104:8097, method_path=/com.tcl.xr.service.AskAiService/chat, request=com.tcl.xr.message.AskAiRequest, response=com.tcl.xr.message.AskAiResponse, server_streaming=True, payload_bytes=395"
    },
    {
      "request_id": 20,
      "success": true,
      "status_code": 0,
      "error": "",
      "latency_ms": 16945.64070017077,
      "first_frame_latency_ms": 10361.102800117806,
      "response_bytes": 46652,
      "start_time": "2026-06-25 19:35:00.468",
      "end_time": "2026-06-25 19:35:17.414",
      "relative_end_second": 49,
      "body_template_index": 10,
      "body_template_label": "Body #10",
      "debug_info": "target=47.94.77.104:8097, method_path=/com.tcl.xr.service.AskAiService/chat, request=com.tcl.xr.message.AskAiRequest, response=com.tcl.xr.message.AskAiResponse, server_streaming=True, payload_bytes=300"
    },
    {
      "request_id": 18,
      "success": true,
      "status_code": 0,
      "error": "",
      "latency_ms": 24651.961999945343,
      "first_frame_latency_ms": 5071.212299866602,
      "response_bytes": 145490,
      "start_time": "2026-06-25 19:34:56.538",
      "end_time": "2026-06-25 19:35:21.190",
      "relative_end_second": 52,
      "body_template_index": 8,
      "body_template_label": "Body #8",
      "debug_info": "target=47.94.77.104:8097, method_path=/com.tcl.xr.service.AskAiService/chat, request=com.tcl.xr.message.AskAiRequest, response=com.tcl.xr.message.AskAiResponse, server_streaming=True, payload_bytes=312"
    },
    {
      "request_id": 19,
      "success": true,
      "status_code": 0,
      "error": "",
      "latency_ms": 23692.70660006441,
      "first_frame_latency_ms": 6192.220899974927,
      "response_bytes": 130428,
      "start_time": "2026-06-25 19:35:00.008",
      "end_time": "2026-06-25 19:35:23.699",
      "relative_end_second": 55,
      "body_template_index": 9,
      "body_template_label": "Body #9",
      "debug_info": "target=47.94.77.104:8097, method_path=/com.tcl.xr.service.AskAiService/chat, request=com.tcl.xr.message.AskAiRequest, response=com.tcl.xr.message.AskAiResponse, server_streaming=True, payload_bytes=318"
    },
    {
      "request_id": 1,
      "success": true,
      "status_code": 0,
      "error": "",
      "latency_ms": 56008.11739987694,
      "first_frame_latency_ms": 1288.1453998852521,
      "response_bytes": 437985,
      "start_time": "2026-06-25 19:34:28.212",
      "end_time": "2026-06-25 19:35:24.220",
      "relative_end_second": 56,
      "body_template_index": 1,
      "body_template_label": "Body #1",
      "debug_info": "target=47.94.77.104:8097, method_path=/com.tcl.xr.service.AskAiService/chat, request=com.tcl.xr.message.AskAiRequest, response=com.tcl.xr.message.AskAiResponse, server_streaming=True, payload_bytes=556"
    },
    {
      "request_id": 22,
      "success": true,
      "status_code": 0,
      "error": "",
      "latency_ms": 17799.5037001092,
      "first_frame_latency_ms": 9197.031600167975,
      "response_bytes": 67532,
      "start_time": "2026-06-25 19:35:09.989",
      "end_time": "2026-06-25 19:35:27.789",
      "relative_end_second": 59,
      "body_template_index": 2,
      "body_template_label": "Body #2",
      "debug_info": "target=47.94.77.104:8097, method_path=/com.tcl.xr.service.AskAiService/chat, request=com.tcl.xr.message.AskAiRequest, response=com.tcl.xr.message.AskAiResponse, server_streaming=True, payload_bytes=357"
    },
    {
      "request_id": 23,
      "success": true,
      "status_code": 0,
      "error": "",
      "latency_ms": 17680.481200106442,
      "first_frame_latency_ms": 9182.232600171119,
      "response_bytes": 57484,
      "start_time": "2026-06-25 19:35:12.833",
      "end_time": "2026-06-25 19:35:30.514",
      "relative_end_second": 62,
      "body_template_index": 3,
      "body_template_label": "Body #3",
      "debug_info": "target=47.94.77.104:8097, method_path=/com.tcl.xr.service.AskAiService/chat, request=com.tcl.xr.message.AskAiRequest, response=com.tcl.xr.message.AskAiResponse, server_streaming=True, payload_bytes=327"
    },
    {
      "request_id": 14,
      "success": true,
      "status_code": 0,
      "error": "",
      "latency_ms": 44402.59009995498,
      "first_frame_latency_ms": 6547.300799982622,
      "response_bytes": 263566,
      "start_time": "2026-06-25 19:34:47.600",
      "end_time": "2026-06-25 19:35:32.003",
      "relative_end_second": 63,
      "body_template_index": 4,
      "body_template_label": "Body #4",
      "debug_info": "target=47.94.77.104:8097, method_path=/com.tcl.xr.service.AskAiService/chat, request=com.tcl.xr.message.AskAiRequest, response=com.tcl.xr.message.AskAiResponse, server_streaming=True, payload_bytes=372"
    },
    {
      "request_id": 11,
      "success": true,
      "status_code": 0,
      "error": "",
      "latency_ms": 51784.93229998276,
      "first_frame_latency_ms": 5041.894500143826,
      "response_bytes": 384555,
      "start_time": "2026-06-25 19:34:40.229",
      "end_time": "2026-06-25 19:35:32.013",
      "relative_end_second": 63,
      "body_template_index": 1,
      "body_template_label": "Body #1",
      "debug_info": "target=47.94.77.104:8097, method_path=/com.tcl.xr.service.AskAiService/chat, request=com.tcl.xr.message.AskAiRequest, response=com.tcl.xr.message.AskAiResponse, server_streaming=True, payload_bytes=556"
    },
    {
      "request_id": 7,
      "success": true,
      "status_code": 0,
      "error": "",
      "latency_ms": 59313.41820000671,
      "first_frame_latency_ms": 943.5296000447124,
      "response_bytes": 477124,
      "start_time": "2026-06-25 19:34:34.884",
      "end_time": "2026-06-25 19:35:34.197",
      "relative_end_second": 65,
      "body_template_index": 7,
      "body_template_label": "Body #7",
      "debug_info": "target=47.94.77.104:8097, method_path=/com.tcl.xr.service.AskAiService/chat, request=com.tcl.xr.message.AskAiRequest, response=com.tcl.xr.message.AskAiResponse, server_streaming=True, payload_bytes=369"
    },
    {
      "request_id": 25,
      "success": true,
      "status_code": 0,
      "error": "",
      "latency_ms": 17005.600600037724,
      "first_frame_latency_ms": 4276.112000225112,
      "response_bytes": 99750,
      "start_time": "2026-06-25 19:35:21.190",
      "end_time": "2026-06-25 19:35:38.196",
      "relative_end_second": 69,
      "body_template_index": 5,
      "body_template_label": "Body #5",
      "debug_info": "target=47.94.77.104:8097, method_path=/com.tcl.xr.service.AskAiService/chat, request=com.tcl.xr.message.AskAiRequest, response=com.tcl.xr.message.AskAiResponse, server_streaming=True, payload_bytes=442"
    },
    {
      "request_id": 28,
      "success": true,
      "status_code": 0,
      "error": "",
      "latency_ms": 13478.947200113907,
      "first_frame_latency_ms": 5582.492700079456,
      "response_bytes": 57708,
      "start_time": "2026-06-25 19:35:27.790",
      "end_time": "2026-06-25 19:35:41.269",
      "relative_end_second": 73,
      "body_template_index": 8,
      "body_template_label": "Body #8",
      "debug_info": "target=47.94.77.104:8097, method_path=/com.tcl.xr.service.AskAiService/chat, request=com.tcl.xr.message.AskAiRequest, response=com.tcl.xr.message.AskAiResponse, server_streaming=True, payload_bytes=312"
    },
    {
      "request_id": 26,
      "success": true,
      "status_code": 0,
      "error": "",
      "latency_ms": 19328.154999995604,
      "first_frame_latency_ms": 5190.012899925932,
      "response_bytes": 124157,
      "start_time": "2026-06-25 19:35:23.700",
      "end_time": "2026-06-25 19:35:43.028",
      "relative_end_second": 74,
      "body_template_index": 6,
      "body_template_label": "Body #6",
      "debug_info": "target=47.94.77.104:8097, method_path=/com.tcl.xr.service.AskAiService/chat, request=com.tcl.xr.message.AskAiRequest, response=com.tcl.xr.message.AskAiResponse, server_streaming=True, payload_bytes=395"
    },
    {
      "request_id": 30,
      "success": true,
      "status_code": 0,
      "error": "",
      "latency_ms": 12923.157700104639,
      "first_frame_latency_ms": 3253.5308999940753,
      "response_bytes": 61571,
      "start_time": "2026-06-25 19:35:32.004",
      "end_time": "2026-06-25 19:35:44.927",
      "relative_end_second": 76,
      "body_template_index": 10,
      "body_template_label": "Body #10",
      "debug_info": "target=47.94.77.104:8097, method_path=/com.tcl.xr.service.AskAiService/chat, request=com.tcl.xr.message.AskAiRequest, response=com.tcl.xr.message.AskAiResponse, server_streaming=True, payload_bytes=300"
    },
    {
      "request_id": 29,
      "success": true,
      "status_code": 0,
      "error": "",
      "latency_ms": 14751.380199799314,
      "first_frame_latency_ms": 2617.5820999778807,
      "response_bytes": 83882,
      "start_time": "2026-06-25 19:35:30.514",
      "end_time": "2026-06-25 19:35:45.265",
      "relative_end_second": 77,
      "body_template_index": 9,
      "body_template_label": "Body #9",
      "debug_info": "target=47.94.77.104:8097, method_path=/com.tcl.xr.service.AskAiService/chat, request=com.tcl.xr.message.AskAiRequest, response=com.tcl.xr.message.AskAiResponse, server_streaming=True, payload_bytes=318"
    },
    {
      "request_id": 21,
      "success": true,
      "status_code": 0,
      "error": "",
      "latency_ms": 44439.75680018775,
      "first_frame_latency_ms": 9044.200600124896,
      "response_bytes": 287407,
      "start_time": "2026-06-25 19:35:05.311",
      "end_time": "2026-06-25 19:35:49.752",
      "relative_end_second": 81,
      "body_template_index": 1,
      "body_template_label": "Body #1",
      "debug_info": "target=47.94.77.104:8097, method_path=/com.tcl.xr.service.AskAiService/chat, request=com.tcl.xr.message.AskAiRequest, response=com.tcl.xr.message.AskAiResponse, server_streaming=True, payload_bytes=556"
    },
    {
      "request_id": 32,
      "success": true,
      "status_code": 0,
      "error": "",
      "latency_ms": 19832.968599861488,
      "first_frame_latency_ms": 8053.779699839652,
      "response_bytes": 89881,
      "start_time": "2026-06-25 19:35:34.198",
      "end_time": "2026-06-25 19:35:54.030",
      "relative_end_second": 85,
      "body_template_index": 2,
      "body_template_label": "Body #2",
      "debug_info": "target=47.94.77.104:8097, method_path=/com.tcl.xr.service.AskAiService/chat, request=com.tcl.xr.message.AskAiRequest, response=com.tcl.xr.message.AskAiResponse, server_streaming=True, payload_bytes=357"
    },
    {
      "request_id": 35,
      "success": true,
      "status_code": 0,
      "error": "",
      "latency_ms": 13643.50500004366,
      "first_frame_latency_ms": 7680.919900070876,
      "response_bytes": 48447,
      "start_time": "2026-06-25 19:35:43.028",
      "end_time": "2026-06-25 19:35:56.672",
      "relative_end_second": 88,
      "body_template_index": 5,
      "body_template_label": "Body #5",
      "debug_info": "target=47.94.77.104:8097, method_path=/com.tcl.xr.service.AskAiService/chat, request=com.tcl.xr.message.AskAiRequest, response=com.tcl.xr.message.AskAiResponse, server_streaming=True, payload_bytes=442"
    },
    {
      "request_id": 33,
      "success": true,
      "status_code": 0,
      "error": "",
      "latency_ms": 21452.642400050536,
      "first_frame_latency_ms": 5666.9966001063585,
      "response_bytes": 106789,
      "start_time": "2026-06-25 19:35:38.197",
      "end_time": "2026-06-25 19:35:59.649",
      "relative_end_second": 91,
      "body_template_index": 3,
      "body_template_label": "Body #3",
      "debug_info": "target=47.94.77.104:8097, method_path=/com.tcl.xr.service.AskAiService/chat, request=com.tcl.xr.message.AskAiRequest, response=com.tcl.xr.message.AskAiResponse, server_streaming=True, payload_bytes=327"
    },
    {
      "request_id": 27,
      "success": true,
      "status_code": 0,
      "error": "",
      "latency_ms": 36795.66080006771,
      "first_frame_latency_ms": 7203.572599915788,
      "response_bytes": 234134,
      "start_time": "2026-06-25 19:35:24.220",
      "end_time": "2026-06-25 19:36:01.016",
      "relative_end_second": 92,
      "body_template_index": 7,
      "body_template_label": "Body #7",
      "debug_info": "target=47.94.77.104:8097, method_path=/com.tcl.xr.service.AskAiService/chat, request=com.tcl.xr.message.AskAiRequest, response=com.tcl.xr.message.AskAiResponse, server_streaming=True, payload_bytes=369"
    },
    {
      "request_id": 24,
      "success": true,
      "status_code": 0,
      "error": "",
      "latency_ms": 45145.765899913386,
      "first_frame_latency_ms": 7868.433499941602,
      "response_bytes": 249411,
      "start_time": "2026-06-25 19:35:17.414",
      "end_time": "2026-06-25 19:36:02.560",
      "relative_end_second": 94,
      "body_template_index": 4,
      "body_template_label": "Body #4",
      "debug_info": "target=47.94.77.104:8097, method_path=/com.tcl.xr.service.AskAiService/chat, request=com.tcl.xr.message.AskAiRequest, response=com.tcl.xr.message.AskAiResponse, server_streaming=True, payload_bytes=372"
    },
    {
      "request_id": 37,
      "success": true,
      "status_code": 0,
      "error": "",
      "latency_ms": 21088.98809994571,
      "first_frame_latency_ms": 9867.099500028417,
      "response_bytes": 91172,
      "start_time": "2026-06-25 19:35:45.266",
      "end_time": "2026-06-25 19:36:06.354",
      "relative_end_second": 98,
      "body_template_index": 7,
      "body_template_label": "Body #7",
      "debug_info": "target=47.94.77.104:8097, method_path=/com.tcl.xr.service.AskAiService/chat, request=com.tcl.xr.message.AskAiRequest, response=com.tcl.xr.message.AskAiResponse, server_streaming=True, payload_bytes=369"
    },
    {
      "request_id": 36,
      "success": true,
      "status_code": 0,
      "error": "",
      "latency_ms": 22288.347200024873,
      "first_frame_latency_ms": 9690.20890002139,
      "response_bytes": 112140,
      "start_time": "2026-06-25 19:35:44.927",
      "end_time": "2026-06-25 19:36:07.215",
      "relative_end_second": 99,
      "body_template_index": 6,
      "body_template_label": "Body #6",
      "debug_info": "target=47.94.77.104:8097, method_path=/com.tcl.xr.service.AskAiService/chat, request=com.tcl.xr.message.AskAiRequest, response=com.tcl.xr.message.AskAiResponse, server_streaming=True, payload_bytes=395"
    },
    {
      "request_id": 38,
      "success": true,
      "status_code": 0,
      "error": "",
      "latency_ms": 17641.017499845475,
      "first_frame_latency_ms": 7825.531899929047,
      "response_bytes": 67599,
      "start_time": "2026-06-25 19:35:49.752",
      "end_time": "2026-06-25 19:36:07.393",
      "relative_end_second": 99,
      "body_template_index": 8,
      "body_template_label": "Body #8",
      "debug_info": "target=47.94.77.104:8097, method_path=/com.tcl.xr.service.AskAiService/chat, request=com.tcl.xr.message.AskAiRequest, response=com.tcl.xr.message.AskAiResponse, server_streaming=True, payload_bytes=312"
    },
    {
      "request_id": 40,
      "success": true,
      "status_code": 0,
      "error": "",
      "latency_ms": 13937.868300126866,
      "first_frame_latency_ms": 5192.679600091651,
      "response_bytes": 54794,
      "start_time": "2026-06-25 19:35:56.673",
      "end_time": "2026-06-25 19:36:10.610",
      "relative_end_second": 102,
      "body_template_index": 10,
      "body_template_label": "Body #10",
      "debug_info": "target=47.94.77.104:8097, method_path=/com.tcl.xr.service.AskAiService/chat, request=com.tcl.xr.message.AskAiRequest, response=com.tcl.xr.message.AskAiResponse, server_streaming=True, payload_bytes=300"
    },
    {
      "request_id": 39,
      "success": true,
      "status_code": 0,
      "error": "",
      "latency_ms": 18468.223799951375,
      "first_frame_latency_ms": 6452.250400092453,
      "response_bytes": 76183,
      "start_time": "2026-06-25 19:35:54.030",
      "end_time": "2026-06-25 19:36:12.498",
      "relative_end_second": 104,
      "body_template_index": 9,
      "body_template_label": "Body #9",
      "debug_info": "target=47.94.77.104:8097, method_path=/com.tcl.xr.service.AskAiService/chat, request=com.tcl.xr.message.AskAiRequest, response=com.tcl.xr.message.AskAiResponse, server_streaming=True, payload_bytes=318"
    },
    {
      "request_id": 41,
      "success": true,
      "status_code": 0,
      "error": "",
      "latency_ms": 13530.843100044876,
      "first_frame_latency_ms": 8270.925800083205,
      "response_bytes": 38043,
      "start_time": "2026-06-25 19:35:59.649",
      "end_time": "2026-06-25 19:36:13.179",
      "relative_end_second": 104,
      "body_template_index": 1,
      "body_template_label": "Body #1",
      "debug_info": "target=47.94.77.104:8097, method_path=/com.tcl.xr.service.AskAiService/chat, request=com.tcl.xr.message.AskAiRequest, response=com.tcl.xr.message.AskAiResponse, server_streaming=True, payload_bytes=556"
    },
    {
      "request_id": 31,
      "success": true,
      "status_code": 0,
      "error": "",
      "latency_ms": 42669.86080002971,
      "first_frame_latency_ms": 7815.878399880603,
      "response_bytes": 264898,
      "start_time": "2026-06-25 19:35:32.013",
      "end_time": "2026-06-25 19:36:14.683",
      "relative_end_second": 106,
      "body_template_index": 1,
      "body_template_label": "Body #1",
      "debug_info": "target=47.94.77.104:8097, method_path=/com.tcl.xr.service.AskAiService/chat, request=com.tcl.xr.message.AskAiRequest, response=com.tcl.xr.message.AskAiResponse, server_streaming=True, payload_bytes=556"
    },
    {
      "request_id": 42,
      "success": true,
      "status_code": 0,
      "error": "",
      "latency_ms": 16759.927600156516,
      "first_frame_latency_ms": 7176.066900137812,
      "response_bytes": 66597,
      "start_time": "2026-06-25 19:36:01.016",
      "end_time": "2026-06-25 19:36:17.776",
      "relative_end_second": 109,
      "body_template_index": 2,
      "body_template_label": "Body #2",
      "debug_info": "target=47.94.77.104:8097, method_path=/com.tcl.xr.service.AskAiService/chat, request=com.tcl.xr.message.AskAiRequest, response=com.tcl.xr.message.AskAiResponse, server_streaming=True, payload_bytes=357"
    },
    {
      "request_id": 45,
      "success": true,
      "status_code": 0,
      "error": "",
      "latency_ms": 13402.322599897161,
      "first_frame_latency_ms": 4683.412800077349,
      "response_bytes": 67247,
      "start_time": "2026-06-25 19:36:07.216",
      "end_time": "2026-06-25 19:36:20.618",
      "relative_end_second": 112,
      "body_template_index": 5,
      "body_template_label": "Body #5",
      "debug_info": "target=47.94.77.104:8097, method_path=/com.tcl.xr.service.AskAiService/chat, request=com.tcl.xr.message.AskAiRequest, response=com.tcl.xr.message.AskAiResponse, server_streaming=True, payload_bytes=442"
    },
    {
      "request_id": 47,
      "success": true,
      "status_code": 0,
      "error": "",
      "latency_ms": 12705.591999925673,
      "first_frame_latency_ms": 3752.070799935609,
      "response_bytes": 74307,
      "start_time": "2026-06-25 19:36:10.611",
      "end_time": "2026-06-25 19:36:23.316",
      "relative_end_second": 115,
      "body_template_index": 7,
      "body_template_label": "Body #7",
      "debug_info": "target=47.94.77.104:8097, method_path=/com.tcl.xr.service.AskAiService/chat, request=com.tcl.xr.message.AskAiRequest, response=com.tcl.xr.message.AskAiResponse, server_streaming=True, payload_bytes=369"
    },
    {
      "request_id": 43,
      "success": true,
      "status_code": 0,
      "error": "",
      "latency_ms": 22150.628400035203,
      "first_frame_latency_ms": 5818.870200077072,
      "response_bytes": 102051,
      "start_time": "2026-06-25 19:36:02.560",
      "end_time": "2026-06-25 19:36:24.710",
      "relative_end_second": 116,
      "body_template_index": 3,
      "body_template_label": "Body #3",
      "debug_info": "target=47.94.77.104:8097, method_path=/com.tcl.xr.service.AskAiService/chat, request=com.tcl.xr.message.AskAiRequest, response=com.tcl.xr.message.AskAiResponse, server_streaming=True, payload_bytes=327"
    },
    {
      "request_id": 48,
      "success": true,
      "status_code": 0,
      "error": "",
      "latency_ms": 13141.390800010413,
      "first_frame_latency_ms": 3087.367800064385,
      "response_bytes": 67512,
      "start_time": "2026-06-25 19:36:12.500",
      "end_time": "2026-06-25 19:36:25.641",
      "relative_end_second": 117,
      "body_template_index": 8,
      "body_template_label": "Body #8",
      "debug_info": "target=47.94.77.104:8097, method_path=/com.tcl.xr.service.AskAiService/chat, request=com.tcl.xr.message.AskAiRequest, response=com.tcl.xr.message.AskAiResponse, server_streaming=True, payload_bytes=312"
    },
    {
      "request_id": 46,
      "success": true,
      "status_code": 0,
      "error": "",
      "latency_ms": 22001.62829994224,
      "first_frame_latency_ms": 6182.3251999448985,
      "response_bytes": 134575,
      "start_time": "2026-06-25 19:36:07.394",
      "end_time": "2026-06-25 19:36:29.395",
      "relative_end_second": 121,
      "body_template_index": 6,
      "body_template_label": "Body #6",
      "debug_info": "target=47.94.77.104:8097, method_path=/com.tcl.xr.service.AskAiService/chat, request=com.tcl.xr.message.AskAiRequest, response=com.tcl.xr.message.AskAiResponse, server_streaming=True, payload_bytes=395"
    },
    {
      "request_id": 49,
      "success": true,
      "status_code": 0,
      "error": "",
      "latency_ms": 17570.69139997475,
      "first_frame_latency_ms": 8225.562399951741,
      "response_bytes": 59805,
      "start_time": "2026-06-25 19:36:13.180",
      "end_time": "2026-06-25 19:36:30.751",
      "relative_end_second": 122,
      "body_template_index": 9,
      "body_template_label": "Body #9",
      "debug_info": "target=47.94.77.104:8097, method_path=/com.tcl.xr.service.AskAiService/chat, request=com.tcl.xr.message.AskAiRequest, response=com.tcl.xr.message.AskAiResponse, server_streaming=True, payload_bytes=318"
    },
    {
      "request_id": 51,
      "success": true,
      "status_code": 0,
      "error": "",
      "latency_ms": 13734.071499900892,
      "first_frame_latency_ms": 8251.987399999052,
      "response_bytes": 46545,
      "start_time": "2026-06-25 19:36:17.777",
      "end_time": "2026-06-25 19:36:31.511",
      "relative_end_second": 123,
      "body_template_index": 1,
      "body_template_label": "Body #1",
      "debug_info": "target=47.94.77.104:8097, method_path=/com.tcl.xr.service.AskAiService/chat, request=com.tcl.xr.message.AskAiRequest, response=com.tcl.xr.message.AskAiResponse, server_streaming=True, payload_bytes=556"
    },
    {
      "request_id": 50,
      "success": true,
      "status_code": 0,
      "error": "",
      "latency_ms": 18037.083700066432,
      "first_frame_latency_ms": 9419.318600092083,
      "response_bytes": 48809,
      "start_time": "2026-06-25 19:36:14.684",
      "end_time": "2026-06-25 19:36:32.721",
      "relative_end_second": 124,
      "body_template_index": 10,
      "body_template_label": "Body #10",
      "debug_info": "target=47.94.77.104:8097, method_path=/com.tcl.xr.service.AskAiService/chat, request=com.tcl.xr.message.AskAiRequest, response=com.tcl.xr.message.AskAiResponse, server_streaming=True, payload_bytes=300"
    },
    {
      "request_id": 34,
      "success": true,
      "status_code": 0,
      "error": "",
      "latency_ms": 52454.36069997959,
      "first_frame_latency_ms": 4992.7114001475275,
      "response_bytes": 305927,
      "start_time": "2026-06-25 19:35:41.269",
      "end_time": "2026-06-25 19:36:33.723",
      "relative_end_second": 125,
      "body_template_index": 4,
      "body_template_label": "Body #4",
      "debug_info": "target=47.94.77.104:8097, method_path=/com.tcl.xr.service.AskAiService/chat, request=com.tcl.xr.message.AskAiRequest, response=com.tcl.xr.message.AskAiResponse, server_streaming=True, payload_bytes=372"
    },
    {
      "request_id": 53,
      "success": true,
      "status_code": 0,
      "error": "",
      "latency_ms": 12900.7170998957,
      "first_frame_latency_ms": 3219.745700014755,
      "response_bytes": 61464,
      "start_time": "2026-06-25 19:36:23.318",
      "end_time": "2026-06-25 19:36:36.218",
      "relative_end_second": 128,
      "body_template_index": 3,
      "body_template_label": "Body #3",
      "debug_info": "target=47.94.77.104:8097, method_path=/com.tcl.xr.service.AskAiService/chat, request=com.tcl.xr.message.AskAiRequest, response=com.tcl.xr.message.AskAiResponse, server_streaming=True, payload_bytes=327"
    },
    {
      "request_id": 55,
      "success": true,
      "status_code": 0,
      "error": "",
      "latency_ms": 14990.650000050664,
      "first_frame_latency_ms": 6195.333200041205,
      "response_bytes": 67318,
      "start_time": "2026-06-25 19:36:25.641",
      "end_time": "2026-06-25 19:36:40.632",
      "relative_end_second": 132,
      "body_template_index": 5,
      "body_template_label": "Body #5",
      "debug_info": "target=47.94.77.104:8097, method_path=/com.tcl.xr.service.AskAiService/chat, request=com.tcl.xr.message.AskAiRequest, response=com.tcl.xr.message.AskAiResponse, server_streaming=True, payload_bytes=442"
    },
    {
      "request_id": 58,
      "success": true,
      "status_code": 0,
      "error": "",
      "latency_ms": 13695.12419984676,
      "first_frame_latency_ms": 5584.584000054747,
      "response_bytes": 57193,
      "start_time": "2026-06-25 19:36:31.511",
      "end_time": "2026-06-25 19:36:45.206",
      "relative_end_second": 136,
      "body_template_index": 8,
      "body_template_label": "Body #8",
      "debug_info": "target=47.94.77.104:8097, method_path=/com.tcl.xr.service.AskAiService/chat, request=com.tcl.xr.message.AskAiRequest, response=com.tcl.xr.message.AskAiResponse, server_streaming=True, payload_bytes=312"
    },
    {
      "request_id": 57,
      "success": true,
      "status_code": 0,
      "error": "",
      "latency_ms": 14971.527700079605,
      "first_frame_latency_ms": 3856.5984999295324,
      "response_bytes": 88034,
      "start_time": "2026-06-25 19:36:30.751",
      "end_time": "2026-06-25 19:36:45.722",
      "relative_end_second": 137,
      "body_template_index": 7,
      "body_template_label": "Body #7",
      "debug_info": "target=47.94.77.104:8097, method_path=/com.tcl.xr.service.AskAiService/chat, request=com.tcl.xr.message.AskAiRequest, response=com.tcl.xr.message.AskAiResponse, server_streaming=True, payload_bytes=369"
    },
    {
      "request_id": 52,
      "success": true,
      "status_code": 0,
      "error": "",
      "latency_ms": 27269.67930002138,
      "first_frame_latency_ms": 5228.267599828541,
      "response_bytes": 156898,
      "start_time": "2026-06-25 19:36:20.619",
      "end_time": "2026-06-25 19:36:47.888",
      "relative_end_second": 139,
      "body_template_index": 2,
      "body_template_label": "Body #2",
      "debug_info": "target=47.94.77.104:8097, method_path=/com.tcl.xr.service.AskAiService/chat, request=com.tcl.xr.message.AskAiRequest, response=com.tcl.xr.message.AskAiResponse, server_streaming=True, payload_bytes=357"
    },
    {
      "request_id": 56,
      "success": true,
      "status_code": 0,
      "error": "",
      "latency_ms": 19081.652000080794,
      "first_frame_latency_ms": 4296.932500088587,
      "response_bytes": 120775,
      "start_time": "2026-06-25 19:36:29.395",
      "end_time": "2026-06-25 19:36:48.477",
      "relative_end_second": 140,
      "body_template_index": 6,
      "body_template_label": "Body #6",
      "debug_info": "target=47.94.77.104:8097, method_path=/com.tcl.xr.service.AskAiService/chat, request=com.tcl.xr.message.AskAiRequest, response=com.tcl.xr.message.AskAiResponse, server_streaming=True, payload_bytes=395"
    },
    {
      "request_id": 59,
      "success": true,
      "status_code": 0,
      "error": "",
      "latency_ms": 18772.629899904132,
      "first_frame_latency_ms": 8748.296699952334,
      "response_bytes": 64313,
      "start_time": "2026-06-25 19:36:32.721",
      "end_time": "2026-06-25 19:36:51.493",
      "relative_end_second": 143,
      "body_template_index": 9,
      "body_template_label": "Body #9",
      "debug_info": "target=47.94.77.104:8097, method_path=/com.tcl.xr.service.AskAiService/chat, request=com.tcl.xr.message.AskAiRequest, response=com.tcl.xr.message.AskAiResponse, server_streaming=True, payload_bytes=318"
    },
    {
      "request_id": 61,
      "success": true,
      "status_code": 0,
      "error": "",
      "latency_ms": 15444.835300091654,
      "first_frame_latency_ms": 10882.775200065225,
      "response_bytes": 36428,
      "start_time": "2026-06-25 19:36:36.218",
      "end_time": "2026-06-25 19:36:51.663",
      "relative_end_second": 143,
      "body_template_index": 1,
      "body_template_label": "Body #1",
      "debug_info": "target=47.94.77.104:8097, method_path=/com.tcl.xr.service.AskAiService/chat, request=com.tcl.xr.message.AskAiRequest, response=com.tcl.xr.message.AskAiResponse, server_streaming=True, payload_bytes=556"
    },
    {
      "request_id": 60,
      "success": true,
      "status_code": 0,
      "error": "",
      "latency_ms": 19794.17820018716,
      "first_frame_latency_ms": 10607.052800012752,
      "response_bytes": 51450,
      "start_time": "2026-06-25 19:36:33.723",
      "end_time": "2026-06-25 19:36:53.518",
      "relative_end_second": 145,
      "body_template_index": 10,
      "body_template_label": "Body #10",
      "debug_info": "target=47.94.77.104:8097, method_path=/com.tcl.xr.service.AskAiService/chat, request=com.tcl.xr.message.AskAiRequest, response=com.tcl.xr.message.AskAiResponse, server_streaming=True, payload_bytes=300"
    },
    {
      "request_id": 62,
      "success": true,
      "status_code": 0,
      "error": "",
      "latency_ms": 16579.65420000255,
      "first_frame_latency_ms": 6272.892100038007,
      "response_bytes": 74990,
      "start_time": "2026-06-25 19:36:40.632",
      "end_time": "2026-06-25 19:36:57.211",
      "relative_end_second": 148,
      "body_template_index": 2,
      "body_template_label": "Body #2",
      "debug_info": "target=47.94.77.104:8097, method_path=/com.tcl.xr.service.AskAiService/chat, request=com.tcl.xr.message.AskAiRequest, response=com.tcl.xr.message.AskAiResponse, server_streaming=True, payload_bytes=357"
    },
    {
      "request_id": 63,
      "success": true,
      "status_code": 0,
      "error": "",
      "latency_ms": 14982.692599995062,
      "first_frame_latency_ms": 3623.399799922481,
      "response_bytes": 72409,
      "start_time": "2026-06-25 19:36:45.207",
      "end_time": "2026-06-25 19:37:00.190",
      "relative_end_second": 151,
      "body_template_index": 3,
      "body_template_label": "Body #3",
      "debug_info": "target=47.94.77.104:8097, method_path=/com.tcl.xr.service.AskAiService/chat, request=com.tcl.xr.message.AskAiRequest, response=com.tcl.xr.message.AskAiResponse, server_streaming=True, payload_bytes=327"
    },
    {
      "request_id": 65,
      "success": true,
      "status_code": 0,
      "error": "",
      "latency_ms": 15904.569400008768,
      "first_frame_latency_ms": 4988.712599966675,
      "response_bytes": 87563,
      "start_time": "2026-06-25 19:36:47.888",
      "end_time": "2026-06-25 19:37:03.793",
      "relative_end_second": 155,
      "body_template_index": 5,
      "body_template_label": "Body #5",
      "debug_info": "target=47.94.77.104:8097, method_path=/com.tcl.xr.service.AskAiService/chat, request=com.tcl.xr.message.AskAiRequest, response=com.tcl.xr.message.AskAiResponse, server_streaming=True, payload_bytes=442"
    },
    {
      "request_id": 66,
      "success": true,
      "status_code": 0,
      "error": "",
      "latency_ms": 19384.191599907354,
      "first_frame_latency_ms": 6113.747600000352,
      "response_bytes": 122810,
      "start_time": "2026-06-25 19:36:48.478",
      "end_time": "2026-06-25 19:37:07.861",
      "relative_end_second": 159,
      "body_template_index": 6,
      "body_template_label": "Body #6",
      "debug_info": "target=47.94.77.104:8097, method_path=/com.tcl.xr.service.AskAiService/chat, request=com.tcl.xr.message.AskAiRequest, response=com.tcl.xr.message.AskAiResponse, server_streaming=True, payload_bytes=395"
    },
    {
      "request_id": 54,
      "success": true,
      "status_code": 0,
      "error": "",
      "latency_ms": 44218.39539986104,
      "first_frame_latency_ms": 5928.646699991077,
      "response_bytes": 247907,
      "start_time": "2026-06-25 19:36:24.710",
      "end_time": "2026-06-25 19:37:08.929",
      "relative_end_second": 160,
      "body_template_index": 4,
      "body_template_label": "Body #4",
      "debug_info": "target=47.94.77.104:8097, method_path=/com.tcl.xr.service.AskAiService/chat, request=com.tcl.xr.message.AskAiRequest, response=com.tcl.xr.message.AskAiResponse, server_streaming=True, payload_bytes=372"
    },
    {
      "request_id": 68,
      "success": true,
      "status_code": 0,
      "error": "",
      "latency_ms": 17343.96279999055,
      "first_frame_latency_ms": 7117.3745999112725,
      "response_bytes": 75355,
      "start_time": "2026-06-25 19:36:51.663",
      "end_time": "2026-06-25 19:37:09.008",
      "relative_end_second": 160,
      "body_template_index": 8,
      "body_template_label": "Body #8",
      "debug_info": "target=47.94.77.104:8097, method_path=/com.tcl.xr.service.AskAiService/chat, request=com.tcl.xr.message.AskAiRequest, response=com.tcl.xr.message.AskAiResponse, server_streaming=True, payload_bytes=312"
    },
    {
      "request_id": 44,
      "success": true,
      "status_code": 0,
      "error": "",
      "latency_ms": 63985.38209986873,
      "first_frame_latency_ms": 5732.405999908224,
      "response_bytes": 370209,
      "start_time": "2026-06-25 19:36:06.355",
      "end_time": "2026-06-25 19:37:10.340",
      "relative_end_second": 162,
      "body_template_index": 4,
      "body_template_label": "Body #4",
      "debug_info": "target=47.94.77.104:8097, method_path=/com.tcl.xr.service.AskAiService/chat, request=com.tcl.xr.message.AskAiRequest, response=com.tcl.xr.message.AskAiResponse, server_streaming=True, payload_bytes=372"
    },
    {
      "request_id": 70,
      "success": true,
      "status_code": 0,
      "error": "",
      "latency_ms": 15950.163800036535,
      "first_frame_latency_ms": 7333.55710003525,
      "response_bytes": 56438,
      "start_time": "2026-06-25 19:36:57.212",
      "end_time": "2026-06-25 19:37:13.162",
      "relative_end_second": 164,
      "body_template_index": 10,
      "body_template_label": "Body #10",
      "debug_info": "target=47.94.77.104:8097, method_path=/com.tcl.xr.service.AskAiService/chat, request=com.tcl.xr.message.AskAiRequest, response=com.tcl.xr.message.AskAiResponse, server_streaming=True, payload_bytes=300"
    },
    {
      "request_id": 71,
      "success": true,
      "status_code": 0,
      "error": "",
      "latency_ms": 15651.150399819016,
      "first_frame_latency_ms": 9149.66439991258,
      "response_bytes": 50943,
      "start_time": "2026-06-25 19:37:00.190",
      "end_time": "2026-06-25 19:37:15.841",
      "relative_end_second": 167,
      "body_template_index": 1,
      "body_template_label": "Body #1",
      "debug_info": "target=47.94.77.104:8097, method_path=/com.tcl.xr.service.AskAiService/chat, request=com.tcl.xr.message.AskAiRequest, response=com.tcl.xr.message.AskAiResponse, server_streaming=True, payload_bytes=556"
    },
    {
      "request_id": 69,
      "success": true,
      "status_code": 0,
      "error": "",
      "latency_ms": 25610.786199802533,
      "first_frame_latency_ms": 7460.226699942723,
      "response_bytes": 126640,
      "start_time": "2026-06-25 19:36:53.518",
      "end_time": "2026-06-25 19:37:19.129",
      "relative_end_second": 170,
      "body_template_index": 9,
      "body_template_label": "Body #9",
      "debug_info": "target=47.94.77.104:8097, method_path=/com.tcl.xr.service.AskAiService/chat, request=com.tcl.xr.message.AskAiRequest, response=com.tcl.xr.message.AskAiResponse, server_streaming=True, payload_bytes=318"
    },
    {
      "request_id": 73,
      "success": true,
      "status_code": 0,
      "error": "",
      "latency_ms": 12700.800500111654,
      "first_frame_latency_ms": 3289.664800046012,
      "response_bytes": 62543,
      "start_time": "2026-06-25 19:37:07.861",
      "end_time": "2026-06-25 19:37:20.562",
      "relative_end_second": 172,
      "body_template_index": 3,
      "body_template_label": "Body #3",
      "debug_info": "target=47.94.77.104:8097, method_path=/com.tcl.xr.service.AskAiService/chat, request=com.tcl.xr.message.AskAiRequest, response=com.tcl.xr.message.AskAiResponse, server_streaming=True, payload_bytes=327"
    },
    {
      "request_id": 72,
      "success": true,
      "status_code": 0,
      "error": "",
      "latency_ms": 17323.288300074637,
      "first_frame_latency_ms": 6457.636600127444,
      "response_bytes": 79182,
      "start_time": "2026-06-25 19:37:03.794",
      "end_time": "2026-06-25 19:37:21.117",
      "relative_end_second": 172,
      "body_template_index": 2,
      "body_template_label": "Body #2",
      "debug_info": "target=47.94.77.104:8097, method_path=/com.tcl.xr.service.AskAiService/chat, request=com.tcl.xr.message.AskAiRequest, response=com.tcl.xr.message.AskAiResponse, server_streaming=True, payload_bytes=357"
    },
    {
      "request_id": 78,
      "success": true,
      "status_code": 0,
      "error": "",
      "latency_ms": 13925.345399882644,
      "first_frame_latency_ms": 5667.948499787599,
      "response_bytes": 65003,
      "start_time": "2026-06-25 19:37:15.841",
      "end_time": "2026-06-25 19:37:29.767",
      "relative_end_second": 181,
      "body_template_index": 8,
      "body_template_label": "Body #8",
      "debug_info": "target=47.94.77.104:8097, method_path=/com.tcl.xr.service.AskAiService/chat, request=com.tcl.xr.message.AskAiRequest, response=com.tcl.xr.message.AskAiResponse, server_streaming=True, payload_bytes=312"
    },
    {
      "request_id": 77,
      "success": true,
      "status_code": 0,
      "error": "",
      "latency_ms": 16794.562199851498,
      "first_frame_latency_ms": 6893.460199935362,
      "response_bytes": 86160,
      "start_time": "2026-06-25 19:37:13.163",
      "end_time": "2026-06-25 19:37:29.957",
      "relative_end_second": 181,
      "body_template_index": 7,
      "body_template_label": "Body #7",
      "debug_info": "target=47.94.77.104:8097, method_path=/com.tcl.xr.service.AskAiService/chat, request=com.tcl.xr.message.AskAiRequest, response=com.tcl.xr.message.AskAiResponse, server_streaming=True, payload_bytes=369"
    },
    {
      "request_id": 79,
      "success": true,
      "status_code": 0,
      "error": "",
      "latency_ms": 11917.623599991202,
      "first_frame_latency_ms": 3019.6402999572456,
      "response_bytes": 68399,
      "start_time": "2026-06-25 19:37:19.129",
      "end_time": "2026-06-25 19:37:31.047",
      "relative_end_second": 182,
      "body_template_index": 9,
      "body_template_label": "Body #9",
      "debug_info": "target=47.94.77.104:8097, method_path=/com.tcl.xr.service.AskAiService/chat, request=com.tcl.xr.message.AskAiRequest, response=com.tcl.xr.message.AskAiResponse, server_streaming=True, payload_bytes=318"
    },
    {
      "request_id": 75,
      "success": true,
      "status_code": 0,
      "error": "",
      "latency_ms": 22122.02989985235,
      "first_frame_latency_ms": 7880.042299861088,
      "response_bytes": 116944,
      "start_time": "2026-06-25 19:37:09.008",
      "end_time": "2026-06-25 19:37:31.130",
      "relative_end_second": 182,
      "body_template_index": 5,
      "body_template_label": "Body #5",
      "debug_info": "target=47.94.77.104:8097, method_path=/com.tcl.xr.service.AskAiService/chat, request=com.tcl.xr.message.AskAiRequest, response=com.tcl.xr.message.AskAiResponse, server_streaming=True, payload_bytes=442"
    },
    {
      "request_id": 67,
      "success": true,
      "status_code": 0,
      "error": "",
      "latency_ms": 43102.24159993231,
      "first_frame_latency_ms": 6703.950399998575,
      "response_bytes": 292614,
      "start_time": "2026-06-25 19:36:51.494",
      "end_time": "2026-06-25 19:37:34.596",
      "relative_end_second": 186,
      "body_template_index": 7,
      "body_template_label": "Body #7",
      "debug_info": "target=47.94.77.104:8097, method_path=/com.tcl.xr.service.AskAiService/chat, request=com.tcl.xr.message.AskAiRequest, response=com.tcl.xr.message.AskAiResponse, server_streaming=True, payload_bytes=369"
    },
    {
      "request_id": 81,
      "success": true,
      "status_code": 0,
      "error": "",
      "latency_ms": 14166.430300101638,
      "first_frame_latency_ms": 10536.761499941349,
      "response_bytes": 30777,
      "start_time": "2026-06-25 19:37:21.118",
      "end_time": "2026-06-25 19:37:35.284",
      "relative_end_second": 187,
      "body_template_index": 1,
      "body_template_label": "Body #1",
      "debug_info": "target=47.94.77.104:8097, method_path=/com.tcl.xr.service.AskAiService/chat, request=com.tcl.xr.message.AskAiRequest, response=com.tcl.xr.message.AskAiResponse, server_streaming=True, payload_bytes=556"
    },
    {
      "request_id": 76,
      "success": true,
      "status_code": 0,
      "error": "",
      "latency_ms": 25514.97680018656,
      "first_frame_latency_ms": 7260.2699000854045,
      "response_bytes": 158543,
      "start_time": "2026-06-25 19:37:10.341",
      "end_time": "2026-06-25 19:37:35.855",
      "relative_end_second": 187,
      "body_template_index": 6,
      "body_template_label": "Body #6",
      "debug_info": "target=47.94.77.104:8097, method_path=/com.tcl.xr.service.AskAiService/chat, request=com.tcl.xr.message.AskAiRequest, response=com.tcl.xr.message.AskAiResponse, server_streaming=True, payload_bytes=395"
    },
    {
      "request_id": 64,
      "success": true,
      "status_code": 0,
      "error": "",
      "latency_ms": 51442.42789992131,
      "first_frame_latency_ms": 4142.774800071493,
      "response_bytes": 315776,
      "start_time": "2026-06-25 19:36:45.723",
      "end_time": "2026-06-25 19:37:37.165",
      "relative_end_second": 188,
      "body_template_index": 4,
      "body_template_label": "Body #4",
      "debug_info": "target=47.94.77.104:8097, method_path=/com.tcl.xr.service.AskAiService/chat, request=com.tcl.xr.message.AskAiRequest, response=com.tcl.xr.message.AskAiResponse, server_streaming=True, payload_bytes=372"
    },
    {
      "request_id": 82,
      "success": true,
      "status_code": 0,
      "error": "",
      "latency_ms": 11648.101500002667,
      "first_frame_latency_ms": 2547.3287999629974,
      "response_bytes": 68687,
      "start_time": "2026-06-25 19:37:29.768",
      "end_time": "2026-06-25 19:37:41.416",
      "relative_end_second": 193,
      "body_template_index": 2,
      "body_template_label": "Body #2",
      "debug_info": "target=47.94.77.104:8097, method_path=/com.tcl.xr.service.AskAiService/chat, request=com.tcl.xr.message.AskAiRequest, response=com.tcl.xr.message.AskAiResponse, server_streaming=True, payload_bytes=357"
    },
    {
      "request_id": 83,
      "success": true,
      "status_code": 0,
      "error": "",
      "latency_ms": 13129.153999965638,
      "first_frame_latency_ms": 2531.624000053853,
      "response_bytes": 69535,
      "start_time": "2026-06-25 19:37:29.958",
      "end_time": "2026-06-25 19:37:43.087",
      "relative_end_second": 194,
      "body_template_index": 3,
      "body_template_label": "Body #3",
      "debug_info": "target=47.94.77.104:8097, method_path=/com.tcl.xr.service.AskAiService/chat, request=com.tcl.xr.message.AskAiRequest, response=com.tcl.xr.message.AskAiResponse, server_streaming=True, payload_bytes=327"
    },
    {
      "request_id": 80,
      "success": true,
      "status_code": 0,
      "error": "",
      "latency_ms": 24714.932299917564,
      "first_frame_latency_ms": 10156.559999799356,
      "response_bytes": 86871,
      "start_time": "2026-06-25 19:37:20.563",
      "end_time": "2026-06-25 19:37:45.279",
      "relative_end_second": 197,
      "body_template_index": 10,
      "body_template_label": "Body #10",
      "debug_info": "target=47.94.77.104:8097, method_path=/com.tcl.xr.service.AskAiService/chat, request=com.tcl.xr.message.AskAiRequest, response=com.tcl.xr.message.AskAiResponse, server_streaming=True, payload_bytes=300"
    },
    {
      "request_id": 85,
      "success": true,
      "status_code": 0,
      "error": "",
      "latency_ms": 15542.252600193024,
      "first_frame_latency_ms": 5239.48370013386,
      "response_bytes": 80910,
      "start_time": "2026-06-25 19:37:31.131",
      "end_time": "2026-06-25 19:37:46.673",
      "relative_end_second": 198,
      "body_template_index": 5,
      "body_template_label": "Body #5",
      "debug_info": "target=47.94.77.104:8097, method_path=/com.tcl.xr.service.AskAiService/chat, request=com.tcl.xr.message.AskAiRequest, response=com.tcl.xr.message.AskAiResponse, server_streaming=True, payload_bytes=442"
    },
    {
      "request_id": 87,
      "success": true,
      "status_code": 0,
      "error": "",
      "latency_ms": 12143.030700040981,
      "first_frame_latency_ms": 3185.2146999444813,
      "response_bytes": 76344,
      "start_time": "2026-06-25 19:37:35.284",
      "end_time": "2026-06-25 19:37:47.427",
      "relative_end_second": 199,
      "body_template_index": 7,
      "body_template_label": "Body #7",
      "debug_info": "target=47.94.77.104:8097, method_path=/com.tcl.xr.service.AskAiService/chat, request=com.tcl.xr.message.AskAiRequest, response=com.tcl.xr.message.AskAiResponse, server_streaming=True, payload_bytes=369"
    },
    {
      "request_id": 74,
      "success": true,
      "status_code": 0,
      "error": "",
      "latency_ms": 38599.8527999036,
      "first_frame_latency_ms": 5450.682499911636,
      "response_bytes": 219244,
      "start_time": "2026-06-25 19:37:08.929",
      "end_time": "2026-06-25 19:37:47.529",
      "relative_end_second": 199,
      "body_template_index": 4,
      "body_template_label": "Body #4",
      "debug_info": "target=47.94.77.104:8097, method_path=/com.tcl.xr.service.AskAiService/chat, request=com.tcl.xr.message.AskAiRequest, response=com.tcl.xr.message.AskAiResponse, server_streaming=True, payload_bytes=372"
    },
    {
      "request_id": 89,
      "success": true,
      "status_code": 0,
      "error": "",
      "latency_ms": 14226.435699965805,
      "first_frame_latency_ms": 6776.267600012943,
      "response_bytes": 50508,
      "start_time": "2026-06-25 19:37:37.166",
      "end_time": "2026-06-25 19:37:51.392",
      "relative_end_second": 203,
      "body_template_index": 9,
      "body_template_label": "Body #9",
      "debug_info": "target=47.94.77.104:8097, method_path=/com.tcl.xr.service.AskAiService/chat, request=com.tcl.xr.message.AskAiRequest, response=com.tcl.xr.message.AskAiResponse, server_streaming=True, payload_bytes=318"
    },
    {
      "request_id": 86,
      "success": true,
      "status_code": 0,
      "error": "",
      "latency_ms": 17587.02199999243,
      "first_frame_latency_ms": 2482.1675000712276,
      "response_bytes": 129664,
      "start_time": "2026-06-25 19:37:34.597",
      "end_time": "2026-06-25 19:37:52.184",
      "relative_end_second": 203,
      "body_template_index": 6,
      "body_template_label": "Body #6",
      "debug_info": "target=47.94.77.104:8097, method_path=/com.tcl.xr.service.AskAiService/chat, request=com.tcl.xr.message.AskAiRequest, response=com.tcl.xr.message.AskAiResponse, server_streaming=True, payload_bytes=395"
    },
    {
      "request_id": 88,
      "success": true,
      "status_code": 0,
      "error": "",
      "latency_ms": 17641.775600146502,
      "first_frame_latency_ms": 6493.0931001435965,
      "response_bytes": 70014,
      "start_time": "2026-06-25 19:37:35.857",
      "end_time": "2026-06-25 19:37:53.498",
      "relative_end_second": 205,
      "body_template_index": 8,
      "body_template_label": "Body #8",
      "debug_info": "target=47.94.77.104:8097, method_path=/com.tcl.xr.service.AskAiService/chat, request=com.tcl.xr.message.AskAiRequest, response=com.tcl.xr.message.AskAiResponse, server_streaming=True, payload_bytes=312"
    },
    {
      "request_id": 90,
      "success": true,
      "status_code": 0,
      "error": "",
      "latency_ms": 13415.065600071102,
      "first_frame_latency_ms": 4639.077699976042,
      "response_bytes": 49126,
      "start_time": "2026-06-25 19:37:41.416",
      "end_time": "2026-06-25 19:37:54.831",
      "relative_end_second": 206,
      "body_template_index": 10,
      "body_template_label": "Body #10",
      "debug_info": "target=47.94.77.104:8097, method_path=/com.tcl.xr.service.AskAiService/chat, request=com.tcl.xr.message.AskAiRequest, response=com.tcl.xr.message.AskAiResponse, server_streaming=True, payload_bytes=300"
    },
    {
      "request_id": 93,
      "success": true,
      "status_code": 0,
      "error": "",
      "latency_ms": 10983.17990009673,
      "first_frame_latency_ms": 2246.701499912888,
      "response_bytes": 56854,
      "start_time": "2026-06-25 19:37:46.674",
      "end_time": "2026-06-25 19:37:57.657",
      "relative_end_second": 209,
      "body_template_index": 3,
      "body_template_label": "Body #3",
      "debug_info": "target=47.94.77.104:8097, method_path=/com.tcl.xr.service.AskAiService/chat, request=com.tcl.xr.message.AskAiRequest, response=com.tcl.xr.message.AskAiResponse, server_streaming=True, payload_bytes=327"
    },
    {
      "request_id": 92,
      "success": true,
      "status_code": 0,
      "error": "",
      "latency_ms": 14737.110800109804,
      "first_frame_latency_ms": 3410.522400168702,
      "response_bytes": 83064,
      "start_time": "2026-06-25 19:37:45.279",
      "end_time": "2026-06-25 19:38:00.016",
      "relative_end_second": 211,
      "body_template_index": 2,
      "body_template_label": "Body #2",
      "debug_info": "target=47.94.77.104:8097, method_path=/com.tcl.xr.service.AskAiService/chat, request=com.tcl.xr.message.AskAiRequest, response=com.tcl.xr.message.AskAiResponse, server_streaming=True, payload_bytes=357"
    },
    {
      "request_id": 95,
      "success": true,
      "status_code": 0,
      "error": "",
      "latency_ms": 14611.081100068986,
      "first_frame_latency_ms": 5925.268500111997,
      "response_bytes": 68242,
      "start_time": "2026-06-25 19:37:47.529",
      "end_time": "2026-06-25 19:38:02.140",
      "relative_end_second": 213,
      "body_template_index": 5,
      "body_template_label": "Body #5",
      "debug_info": "target=47.94.77.104:8097, method_path=/com.tcl.xr.service.AskAiService/chat, request=com.tcl.xr.message.AskAiRequest, response=com.tcl.xr.message.AskAiResponse, server_streaming=True, payload_bytes=442"
    },
    {
      "request_id": 97,
      "success": true,
      "status_code": 0,
      "error": "",
      "latency_ms": 15066.65900000371,
      "first_frame_latency_ms": 3520.78969986178,
      "response_bytes": 99565,
      "start_time": "2026-06-25 19:37:52.185",
      "end_time": "2026-06-25 19:38:07.251",
      "relative_end_second": 219,
      "body_template_index": 7,
      "body_template_label": "Body #7",
      "debug_info": "target=47.94.77.104:8097, method_path=/com.tcl.xr.service.AskAiService/chat, request=com.tcl.xr.message.AskAiRequest, response=com.tcl.xr.message.AskAiResponse, server_streaming=True, payload_bytes=369"
    },
    {
      "request_id": 96,
      "success": true,
      "status_code": 0,
      "error": "",
      "latency_ms": 17789.365299977362,
      "first_frame_latency_ms": 3200.1869999803603,
      "response_bytes": 134760,
      "start_time": "2026-06-25 19:37:51.393",
      "end_time": "2026-06-25 19:38:09.182",
      "relative_end_second": 220,
      "body_template_index": 6,
      "body_template_label": "Body #6",
      "debug_info": "target=47.94.77.104:8097, method_path=/com.tcl.xr.service.AskAiService/chat, request=com.tcl.xr.message.AskAiRequest, response=com.tcl.xr.message.AskAiResponse, server_streaming=True, payload_bytes=395"
    },
    {
      "request_id": 98,
      "success": true,
      "status_code": 0,
      "error": "",
      "latency_ms": 16005.266699939966,
      "first_frame_latency_ms": 5053.977199830115,
      "response_bytes": 82865,
      "start_time": "2026-06-25 19:37:53.498",
      "end_time": "2026-06-25 19:38:09.504",
      "relative_end_second": 221,
      "body_template_index": 8,
      "body_template_label": "Body #8",
      "debug_info": "target=47.94.77.104:8097, method_path=/com.tcl.xr.service.AskAiService/chat, request=com.tcl.xr.message.AskAiRequest, response=com.tcl.xr.message.AskAiResponse, server_streaming=True, payload_bytes=312"
    },
    {
      "request_id": 99,
      "success": true,
      "status_code": 0,
      "error": "",
      "latency_ms": 15851.203399943188,
      "first_frame_latency_ms": 5971.501699881628,
      "response_bytes": 77310,
      "start_time": "2026-06-25 19:37:54.832",
      "end_time": "2026-06-25 19:38:10.683",
      "relative_end_second": 222,
      "body_template_index": 9,
      "body_template_label": "Body #9",
      "debug_info": "target=47.94.77.104:8097, method_path=/com.tcl.xr.service.AskAiService/chat, request=com.tcl.xr.message.AskAiRequest, response=com.tcl.xr.message.AskAiResponse, server_streaming=True, payload_bytes=318"
    },
    {
      "request_id": 100,
      "success": true,
      "status_code": 0,
      "error": "",
      "latency_ms": 14307.791899889708,
      "first_frame_latency_ms": 5249.138299841434,
      "response_bytes": 69112,
      "start_time": "2026-06-25 19:37:57.658",
      "end_time": "2026-06-25 19:38:11.965",
      "relative_end_second": 223,
      "body_template_index": 10,
      "body_template_label": "Body #10",
      "debug_info": "target=47.94.77.104:8097, method_path=/com.tcl.xr.service.AskAiService/chat, request=com.tcl.xr.message.AskAiRequest, response=com.tcl.xr.message.AskAiResponse, server_streaming=True, payload_bytes=300"
    },
    {
      "request_id": 84,
      "success": true,
      "status_code": 0,
      "error": "",
      "latency_ms": 41792.903899913654,
      "first_frame_latency_ms": 5140.771299833432,
      "response_bytes": 256980,
      "start_time": "2026-06-25 19:37:31.047",
      "end_time": "2026-06-25 19:38:12.840",
      "relative_end_second": 224,
      "body_template_index": 4,
      "body_template_label": "Body #4",
      "debug_info": "target=47.94.77.104:8097, method_path=/com.tcl.xr.service.AskAiService/chat, request=com.tcl.xr.message.AskAiRequest, response=com.tcl.xr.message.AskAiResponse, server_streaming=True, payload_bytes=372"
    },
    {
      "request_id": 94,
      "success": true,
      "status_code": 0,
      "error": "",
      "latency_ms": 37846.711199963465,
      "first_frame_latency_ms": 5364.7056999616325,
      "response_bytes": 285346,
      "start_time": "2026-06-25 19:37:47.428",
      "end_time": "2026-06-25 19:38:25.275",
      "relative_end_second": 237,
      "body_template_index": 4,
      "body_template_label": "Body #4",
      "debug_info": "target=47.94.77.104:8097, method_path=/com.tcl.xr.service.AskAiService/chat, request=com.tcl.xr.message.AskAiRequest, response=com.tcl.xr.message.AskAiResponse, server_streaming=True, payload_bytes=372"
    },
    {
      "request_id": 91,
      "success": true,
      "status_code": 0,
      "error": "",
      "latency_ms": 93265.70870005526,
      "first_frame_latency_ms": 5829.753800062463,
      "response_bytes": 1182211,
      "start_time": "2026-06-25 19:37:43.088",
      "end_time": "2026-06-25 19:39:16.353",
      "relative_end_second": 288,
      "body_template_index": 1,
      "body_template_label": "Body #1",
      "debug_info": "target=47.94.77.104:8097, method_path=/com.tcl.xr.service.AskAiService/chat, request=com.tcl.xr.message.AskAiRequest, response=com.tcl.xr.message.AskAiResponse, server_streaming=True, payload_bytes=556"
    }
  ]
}